<?xml version="1.0" encoding="utf-8"?>
<!DOCTYPE hibernate-mapping PUBLIC "-//Hibernate/Hibernate Mapping DTD 3.0//EN"
        "http://www.hibernate.org/dtd/hibernate-mapping-3.0.dtd">

<hibernate-mapping package="com.forsrc.pojo">
    <class name="Role" table="t_role" lazy="false" dynamic-update="true" dynamic-insert="true"
           select-before-update="true">
        <id name="id" type="java.lang.Long">
            <column name="id"/>
            <generator class="increment"/>
        </id>


        <version name="version" column="version" type="integer"></version>

        <!--
        <timestamp name="updateOn" column="update_on" generated="always"></timestamp>
        -->

        <property name="name" type="java.lang.String" update="false">
            <column name="name" not-null="true" length="30"/>
        </property>

        <property name="createOn" type="java.util.Date" update="false" insert="false" generated="insert" access="field">
            <column name="create_on" default="CURRENT_TIMESTAMP" not-null="true"/>
        </property>

        <property name="updateOn" type="java.util.Date">
            <column name="update_on" default="CURRENT_TIMESTAMP" not-null="true"/>
        </property>
        <property name="status" type="java.lang.Integer" update="false">
            <column name="status" default="1" length="1" not-null="true"/>
        </property>
    </class>
    <sql-query name="sql_role_updateName">
        <![CDATA[
            UPDATE t_role SET name = :name WHERE id = :id and status = 1
         ]]>
    </sql-query>
    <sql-query name="sql_role_getRoles" read-only="true">
        <![CDATA[
             SELECT
                    obj.id, obj.name, obj.url, obj.parentId, obj.create_on, obj.update_on, obj.version, obj.status
             FROM
                    t_role obj
             WHERE
                    obj.status = 1

         ]]>
        <return alias="obj" class="com.forsrc.pojo.Role"/>
    </sql-query>
    
    <sql-query name="sql_role_init" read-only="false">
        <![CDATA[
            INSERT INTO t_role (id, name, version, status) VALUES (1, 'ROLE_ADMIN', 0, 1);
            INSERT INTO t_role (id, name, version, status) VALUES (2, 'ROLE_USER',  0, 1);
            INSERT INTO t_role (id, name, version, status) VALUES (3, 'ROLE_TEST',  0, 1);

         ]]>
    </sql-query>

    <database-object>
        <create>
        </create>
        <drop></drop>
    </database-object>
</hibernate-mapping>
